aportalsmp/__init__.py
aportalsmp/account.py
aportalsmp/auth.py
aportalsmp/gifts.py
aportalsmp/handlers.py
aportalsmp/offers.py
aportalsmp/classes/Exceptions.py
aportalsmp/classes/Objects.py
aportalsmp/classes/__init__.py
aportalsmp/utils/__init__.py
aportalsmp/utils/collections_ids.py
aportalsmp/utils/functions.py
aportalsmp/utils/other.py
portals bot/__init__.py
portals bot/ddd.py
portals bot/main.py
portals bot/similarity.py
portals bot/test2.py
aportalsmp-1.2.3.4.dist-info/METADATA
aportalsmp-1.2.3.4.dist-info/WHEEL
aportalsmp-1.2.3.4.dist-info/top_level.txt
aportalsmp-1.2.3.4.dist-info/RECORD
